{
  "schemaVersion": "1.0",
  "id": "the-moon-metal",
  "title": "El metal de la luna",
  "titleRu": "Металл Луны",
  "originalTitle": "The Moon Metal",
  "author": {
    "id": "garrett-p-serviss",
    "name": "Garrett P. Serviss"
  },
  "genres": [
    "Фантастика"
  ],
  "synopsisRu": "Когда открытие золота у Южного полюса разрушает мировую финансовую систему, загадочный доктор Макс Сикс предлагает заменить его артемизием — прекрасным новым металлом из своей шахты в Скалистых горах. Молодой инженер Эндрю Холл раскрывает невероятную тайну: металл добывается прямо с Луны с помощью гигантского параболического зеркала.",
  "levels": {
    "a1": {
      "available": true,
      "chapterCount": 4
    },
    "a2": {
      "available": true,
      "chapterCount": 4
    },
    "b1": {
      "available": true,
      "chapterCount": 4
    },
    "b2": {
      "available": true,
      "chapterCount": 4
    },
    "c1": {
      "available": true,
      "chapterCount": 4
    },
    "c2": {
      "available": true,
      "chapterCount": 4
    }
  }
}
