{
  "schemaVersion": "1.0",
  "id": "a-tale-of-two-cities",
  "title": "Historia de dos ciudades",
  "titleRu": "Повесть о двух городах",
  "originalTitle": "A Tale of Two Cities",
  "author": {
    "id": "charles-dickens",
    "name": "Charles Dickens"
  },
  "genres": [
    "Историческое",
    "Драма",
    "Революция"
  ],
  "synopsisRu": "Лондон и Париж накануне и во время Французской революции, любовь и самопожертвование. Роман Чарльза Диккенса.",
  "levels": {
    "a1": {
      "available": false,
      "chapterCount": 0
    },
    "a2": {
      "available": true,
      "chapterCount": 8
    },
    "b1": {
      "available": true,
      "chapterCount": 8
    },
    "b2": {
      "available": true,
      "chapterCount": 8
    },
    "c1": {
      "available": true,
      "chapterCount": 8
    },
    "c2": {
      "available": false,
      "chapterCount": 0
    }
  }
}
