{
  "schemaVersion": "1.0",
  "id": "oliver-twist",
  "title": "Oliver Twist",
  "titleRu": "Оливер Твист",
  "originalTitle": "Oliver Twist",
  "author": {
    "id": "charles-dickens",
    "name": "Charles Dickens"
  },
  "genres": [
    "Роман",
    "Социальная драма",
    "Лондон"
  ],
  "synopsisRu": "Сирота Оливер Твист попадает из работного дома в воровскую шайку лондонского дна. Роман Чарльза Диккенса.",
  "levels": {
    "a1": {
      "available": false,
      "chapterCount": 0
    },
    "a2": {
      "available": true,
      "chapterCount": 8
    },
    "b1": {
      "available": true,
      "chapterCount": 8
    },
    "b2": {
      "available": true,
      "chapterCount": 8
    },
    "c1": {
      "available": true,
      "chapterCount": 8
    },
    "c2": {
      "available": false,
      "chapterCount": 0
    }
  }
}
