{
  "schemaVersion": "1.0",
  "id": "the-adventure-of-the-lions-mane",
  "title": "La aventura de la melena del león",
  "titleRu": "Приключение «Гривы льва»",
  "originalTitle": "The Adventure of the Lion's Mane",
  "author": {
    "id": "arthur-conan-doyle",
    "name": "Arthur Conan Doyle"
  },
  "genres": [
    "Детектив",
    "Шерлок Холмс"
  ],
  "synopsisRu": "Шерлок Холмс, живущий на покое в Сассексе, расследует гибель учителя, найденного с загадочными красными полосами на спине и со странными последними словами «грива льва». Поначалу подозрения падают на угрюмого математика Мёрдока, однако истинным убийцей оказывается гигантская ядовитая медуза Cyanea Capillata.",
  "levels": {
    "a1": {
      "available": false,
      "chapterCount": 0
    },
    "a2": {
      "available": true,
      "chapterCount": 1
    },
    "b1": {
      "available": true,
      "chapterCount": 1
    },
    "b2": {
      "available": true,
      "chapterCount": 1
    },
    "c1": {
      "available": true,
      "chapterCount": 1
    },
    "c2": {
      "available": false,
      "chapterCount": 0
    }
  }
}
