{
  "schemaVersion": "1.0",
  "id": "easy-spanish-209",
  "title": "Mensajes de audio",
  "titleRu": "Аудиосообщения",
  "originalTitle": "Mensajes de audio",
  "author": {
    "id": "easy-spanish",
    "name": "Easy Spanish"
  },
  "genres": [
    "Подкаст"
  ],
  "synopsisRu": "Ты оставил нам голосовое сообщение на www.easyspanish.fm? В этом выпуске мы делимся некоторыми из присланных нам аудио, а если ты ещё не отправил сообщение, можешь сделать это прямо сейчас — и мы прокомментируем его в одном из ближайших выпусков!",
  "source": {
    "name": "Easy Spanish · эпизод 209",
    "url": "https://play.easyspanish.fm/episodes/vts4fc9qjgdi4i9ner3r3"
  },
  "levels": {
    "a1": {
      "available": false,
      "chapterCount": 0
    },
    "a2": {
      "available": false,
      "chapterCount": 0
    },
    "b1": {
      "available": true,
      "chapterCount": 1
    },
    "b2": {
      "available": false,
      "chapterCount": 0
    },
    "c1": {
      "available": false,
      "chapterCount": 0
    },
    "c2": {
      "available": false,
      "chapterCount": 0
    }
  }
}
