{
  "schemaVersion": "1.0",
  "id": "the-three-musketeers",
  "title": "Los tres mosqueteros",
  "titleRu": "Три мушкетёра",
  "originalTitle": "The Three Musketeers",
  "author": {
    "id": "alexandre-dumas",
    "name": "Alexandre Dumas"
  },
  "genres": [
    "Приключения",
    "Историческое",
    "Интрига"
  ],
  "synopsisRu": "Молодой гасконец д'Артаньян едет в Париж и вместе с тремя мушкетёрами короля ввязывается в интриги вокруг королевы. Роман Александра Дюма.",
  "levels": {
    "a1": {
      "available": false,
      "chapterCount": 0
    },
    "a2": {
      "available": true,
      "chapterCount": 10
    },
    "b1": {
      "available": true,
      "chapterCount": 10
    },
    "b2": {
      "available": true,
      "chapterCount": 10
    },
    "c1": {
      "available": true,
      "chapterCount": 10
    },
    "c2": {
      "available": false,
      "chapterCount": 0
    }
  }
}
